Classfile /home/ADMSK/kdtemnen/IdeaProjects/bcel-learn/target/classes/ru/temnenkov/bl/problem01/HelloWorldJavaImpl.class
  Last modified 16.02.2025; size 567 bytes
  MD5 checksum 420284dd005e84d6a0522d2f9117a29e
  Compiled from "HelloWorldJavaImpl.java"
public class ru.temnenkov.bl.problem01.HelloWorldJavaImpl
  minor version: 0
  major version: 65
  flags: ACC_PUBLIC, ACC_SUPER
Constant pool:
   #1 = Methodref          #2.#3          // java/lang/Object."<init>":()V
   #2 = Class              #4             // java/lang/Object
   #3 = NameAndType        #5:#6          // "<init>":()V
   #4 = Utf8               java/lang/Object
   #5 = Utf8               <init>
   #6 = Utf8               ()V
   #7 = Fieldref           #8.#9          // java/lang/System.out:Ljava/io/PrintStream;
   #8 = Class              #10            // java/lang/System
   #9 = NameAndType        #11:#12        // out:Ljava/io/PrintStream;
  #10 = Utf8               java/lang/System
  #11 = Utf8               out
  #12 = Utf8               Ljava/io/PrintStream;
  #13 = String             #14            // Hello World!
  #14 = Utf8               Hello World!
  #15 = Methodref          #16.#17        // java/io/PrintStream.println:(Ljava/lang/String;)V
  #16 = Class              #18            // java/io/PrintStream
  #17 = NameAndType        #19:#20        // println:(Ljava/lang/String;)V
  #18 = Utf8               java/io/PrintStream
  #19 = Utf8               println
  #20 = Utf8               (Ljava/lang/String;)V
  #21 = Class              #22            // ru/temnenkov/bl/problem01/HelloWorldJavaImpl
  #22 = Utf8               ru/temnenkov/bl/problem01/HelloWorldJavaImpl
  #23 = Utf8               Code
  #24 = Utf8               LineNumberTable
  #25 = Utf8               LocalVariableTable
  #26 = Utf8               this
  #27 = Utf8               Lru/temnenkov/bl/problem01/HelloWorldJavaImpl;
  #28 = Utf8               printHelloWorld
  #29 = Utf8               SourceFile
  #30 = Utf8               HelloWorldJavaImpl.java
{
  public ru.temnenkov.bl.problem01.HelloWorldJavaImpl();
    descriptor: ()V
    flags: ACC_PUBLIC
    Code:
      stack=1, locals=1, args_size=1
         0: aload_0
         1: invokespecial #1                  // Method java/lang/Object."<init>":()V
         4: return
      LineNumberTable:
        line 3: 0
      LocalVariableTable:
        Start  Length  Slot  Name   Signature
            0       5     0  this   Lru/temnenkov/bl/problem01/HelloWorldJavaImpl;

  void printHelloWorld();
    descriptor: ()V
    flags:
    Code:
      stack=2, locals=1, args_size=1
         0: getstatic     #7                  // Field java/lang/System.out:Ljava/io/PrintStream;
         3: ldc           #13                 // String Hello World!
         5: invokevirtual #15                 // Method java/io/PrintStream.println:(Ljava/lang/String;)V
         8: return
      LineNumberTable:
        line 5: 0
        line 6: 8
      LocalVariableTable:
        Start  Length  Slot  Name   Signature
            0       9     0  this   Lru/temnenkov/bl/problem01/HelloWorldJavaImpl;
}
SourceFile: "HelloWorldJavaImpl.java"
